Metadata-Version: 2.4
Name: PyMLST
Version: 2.2.2
Summary: python Mlst Local Search Tool
Home-page: https://github.com/bvalot/pyMLST.git
Download-URL: https://github.com/bvalot/pyMLST/archive/refs/tags/2.2.2.tar.gz
Author: Benoit Valot
Author-email: benoit.valot@univ-fcomte.fr
License: GPLv3
Keywords: cgMLST,MLST,bacterial genome
Classifier: Development Status :: 5 - Production/Stable
Classifier: Intended Audience :: Developers
Classifier: Topic :: Software Development :: Libraries
Classifier: License :: OSI Approved :: GNU General Public License v3 (GPLv3)
Classifier: Programming Language :: Python :: 3.7
Requires-Python: >=3.7.0
License-File: LICENSE
Requires-Dist: biopython>=1.78
Requires-Dist: click>=7.1
Requires-Dist: pytest>=6.2
Requires-Dist: sqlalchemy<2,>=1.4
Requires-Dist: networkx>=2.5
Requires-Dist: decorator>=4.4
Requires-Dist: requests>=2.23
Requires-Dist: pandas>=1.2
Requires-Dist: numpy>=1.20.0
Requires-Dist: beautifulsoup4>=4.9
Requires-Dist: questionary>=1.9
Requires-Dist: setuptools>=44.0
Requires-Dist: alembic>=1.6
Requires-Dist: GitPython>=3.1
Dynamic: author
Dynamic: author-email
Dynamic: classifier
Dynamic: description
Dynamic: description-content-type
Dynamic: download-url
Dynamic: home-page
Dynamic: keywords
Dynamic: license
Dynamic: license-file
Dynamic: requires-dist
Dynamic: requires-python
Dynamic: summary
